{
  "name": "Bodyweight Squat",
  "category": "Legs",
  "url": "https://www.simplyfitness.com/pages/bodyweight-squat",
  "lead": "Exercise for thigh, glutes, calves and core muscles",
  "instructions": {
    "starting position": "Stand upright with your feet slightly wider than hip-width apart. Hold your arms out in front of you.",
    "execution": "Keeping your chest up and back straight, brace your core while you push your hips backwards into a sitting position. Lower yourself until your thighs are parallel or close to parallel with the ground. Pause and then push yourself back up through your whole foot to the starting position. Keep your knees from caving in at any point during the movement."
  },
  "equipment": [],
  "main_muscles": [
    "Thigh and Glute Muscles"
  ],
  "secondary_muscles": [
    "Calves",
    "Front deltoids"
  ]
}