{
  "name": "Duck Walk",
  "category": "Legs",
  "url": "https://www.simplyfitness.com/pages/duck-walk",
  "lead": "Exercise for thigh, glute muscles and calves",
  "instructions": {
    "starting position": "Stand with your feet shoulder-width apart.",
    "execution": "Squat down into a sitting position by pushing your hips back. Sink into a deep squat without lifting your feet from the floor. Keep your chest tall and brace your core. You can hold your arms out in the air to help with balance. While maintaining the same distance from the floor, take one small step forward with one foot. Repeat with the other foot. You can take steps backwards as well."
  },
  "equipment": [],
  "main_muscles": [
    "Thigh and Glute Muscles"
  ],
  "secondary_muscles": [
    "Calves"
  ]
}